consumableai/__init__.py
consumableai/cli.py
consumableai-1.0.3.data/scripts/cli.py
consumableai-1.0.3.dist-info/LICENSE
consumableai-1.0.3.dist-info/METADATA
consumableai-1.0.3.dist-info/WHEEL
consumableai-1.0.3.dist-info/entry_points.txt
consumableai-1.0.3.dist-info/top_level.txt
consumableai-1.0.3.dist-info/RECORD
