Metadata-Version: 2.1
Name: consumableai
Version: 1.0.3
Summary: UNKNOWN
Home-page: UNKNOWN
License: UNKNOWN
Platform: UNKNOWN
License-File: LICENSE
Requires-Dist: pandas
Requires-Dist: pyyaml
Requires-Dist: click
Requires-Dist: psycopg2-binary
Requires-Dist: requests
Requires-Dist: pathlib
